AUTHORS.rst
CONTRIBUTING.rst
HISTORY.rst
LICENSE
MANIFEST.in
README.rst
pyproject.toml
setup.cfg
setup.py
docs/Makefile
docs/authors.rst
docs/conf.py
docs/contributing.rst
docs/history.rst
docs/index.rst
docs/installation.rst
docs/make.bat
docs/modules.rst
docs/tutorial.rst
docs/.ipynb_checkpoints/authors-checkpoint.rst
docs/.ipynb_checkpoints/installation-checkpoint.rst
docs/.ipynb_checkpoints/readme-checkpoint.rst
docs/figures/plot_climatology.png
docs/figures/plot_step.png
docs/figures/plot_tracks.png
docs/figures/readme.gif
docs/figures/.ipynb_checkpoints/plot_climatology-checkpoint.png
docs/figures/.ipynb_checkpoints/plot_tracks-checkpoint.png
tests/__init__.py
tests/test_wavebreaking.py
tests/.ipynb_checkpoints/__init__-checkpoint.py
tests/.ipynb_checkpoints/test_wavebreaking-checkpoint.py
tests/data/demo_data.nc
tests/data/.ipynb_checkpoints/test_data-checkpoint.txt
wavebreaking/__init__.py
wavebreaking.egg-info/PKG-INFO
wavebreaking.egg-info/SOURCES.txt
wavebreaking.egg-info/dependency_links.txt
wavebreaking.egg-info/not-zip-safe
wavebreaking.egg-info/requires.txt
wavebreaking.egg-info/top_level.txt
wavebreaking.egg-info/.ipynb_checkpoints/PKG-INFO-checkpoint
wavebreaking.egg-info/.ipynb_checkpoints/SOURCES-checkpoint.txt
wavebreaking.egg-info/.ipynb_checkpoints/dependency_links-checkpoint.txt
wavebreaking.egg-info/.ipynb_checkpoints/not-zip-safe-checkpoint
wavebreaking.egg-info/.ipynb_checkpoints/requires-checkpoint.txt
wavebreaking.egg-info/.ipynb_checkpoints/top_level-checkpoint.txt
wavebreaking/indices/__init__.py
wavebreaking/indices/contour_index.py
wavebreaking/indices/cutoff_index.py
wavebreaking/indices/overturning_index.py
wavebreaking/indices/streamer_index.py
wavebreaking/processing/__init__.py
wavebreaking/processing/events.py
wavebreaking/processing/plots.py
wavebreaking/processing/spatial.py
wavebreaking/utils/__init__.py
wavebreaking/utils/data_utils.py
wavebreaking/utils/index_utils.py
wavebreaking/utils/plot_utils.py