Metadata-Version: 2.1
Name: wavebreaking
Version: 0.3.5
Summary: Detect, classify, and track Rossby Wave Breaking (RWB).
Home-page: https://github.com/skaderli/wavebreaking
Author: Severin Kaderli
Author-email: severin.kaderli@unibe.ch
License: MIT license
Keywords: wavebreaking
Classifier: Intended Audience :: Developers
Classifier: License :: OSI Approved :: MIT License
Classifier: Natural Language :: English
Classifier: Programming Language :: Python :: 3
Classifier: Operating System :: OS Independent
Classifier: Intended Audience :: Science/Research
Classifier: Topic :: Scientific/Engineering :: Atmospheric Science
Requires-Python: >=3.8
License-File: LICENSE
License-File: AUTHORS.rst
